{
  "slug": "militia",
  "name": "Militia",
  "nameEn": "Militia",
  "category": "infantry",
  "faction": "standard",
  "country": "XX",
  "countryName": "XX",
  "tier": "C",
  "obtainability": "free",
  "shortDesc": "Unité infantry — XX.",
  "longDesc": "A troop composed of ordinary civilians with weak attack. It belongs to light infantry.",
  "stats": {
    "atk": [
      25,
      25,
      25,
      25,
      25,
      25,
      25,
      25,
      25,
      25,
      25,
      25
    ],
    "def": [
      5,
      5,
      5,
      5,
      5,
      5,
      5,
      5,
      5,
      5,
      5,
      5
    ],
    "hp": [
      135,
      135,
      135,
      135,
      135,
      135,
      135,
      135,
      135,
      135,
      135,
      135
    ],
    "mov": [
      6,
      6,
      6,
      6,
      6,
      6,
      6,
      6,
      6,
      6,
      6,
      6
    ],
    "rng": [
      1,
      1,
      1,
      1,
      1,
      1,
      1,
      1,
      1,
      1,
      1,
      1
    ]
  },
  "perks": [],
  "recommendedGenerals": [],
  "levelingPriority": [],
  "faqs": [],
  "sources": [
    "Données extraites des fichiers de jeu European War 6: 1914"
  ],
  "armyId": 10001,
  "image": {
    "sprite": "/img/ew6/armies/10001.webp",
    "lvl12": null
  },
  "preliminary": true
}