{
  "slug": "harrier",
  "name": "Harrier",
  "nameEn": "Harrier",
  "category": "airforce",
  "faction": "standard",
  "country": "GB",
  "countryName": "Royaume-Uni",
  "tier": "A",
  "obtainability": "shop",
  "shortDesc": "Avion de combat britannique à décollage vertical (VTOL).",
  "longDesc": "Premier avion de combat opérationnel à décollage vertical. Célèbre pour son rôle aux Malouines.",
  "stats": {
    "atk": [
      74,
      74,
      83,
      83,
      92,
      92,
      100,
      100,
      109,
      109,
      109,
      118
    ],
    "def": [
      16,
      24,
      24,
      24,
      24,
      31,
      31,
      31,
      31,
      39,
      39,
      39
    ],
    "hp": [
      395,
      395,
      395,
      495,
      495,
      495,
      495,
      575,
      575,
      575,
      645,
      645
    ],
    "mov": [
      13,
      14,
      14,
      14,
      14,
      15,
      15,
      15,
      15,
      16,
      16,
      16
    ],
    "rng": [
      3,
      3,
      3,
      3,
      3,
      3,
      3,
      3,
      3,
      3,
      3,
      3
    ],
    "atkMin": [
      60,
      60,
      69,
      69,
      78,
      78,
      86,
      86,
      95,
      95,
      95,
      104
    ],
    "atkMax": [
      74,
      74,
      83,
      83,
      92,
      92,
      100,
      100,
      109,
      109,
      109,
      118
    ],
    "rngMin": [
      2,
      2,
      2,
      2,
      2,
      2,
      2,
      2,
      2,
      2,
      2,
      2
    ]
  },
  "perks": [
    {
      "lvl": 1,
      "type": "passive",
      "icon": "🦅",
      "name": "Supériorité aérienne",
      "desc": "Peut décoller à 1 case d'un porte-avions. Ignore tous les effets de terrain sur la mobilité et toutes les mines. L'ennemi ne peut pas riposter. L'efficacité au combat ne baisse pas quand les PV diminuent.",
      "milestone": true,
      "nameEn": "Air superiority",
      "nameDe": "Luftüberlegenheit",
      "descEn": "Can take off within 1 tile of an aircraft carrier. Ignores all terrain effects on mobility and all mines. The enemy cannot counter-attack. Combat effectiveness does not decrease when HP drops.",
      "descDe": "Kann im Umkreis von 1 Feld um einen Flugzeugträger starten. Ignoriert alle Geländeeffekte auf die Mobilität und alle Minen. Der Feind kann nicht kontern. Die Kampfeffektivität sinkt nicht, wenn die TP abnehmen."
    },
    {
      "lvl": 1,
      "type": "active-skill",
      "icon": "⭐",
      "name": "Vectorisation de poussée",
      "desc": "40% de chances d'esquiver les dégâts des unités terrestres ou navales, 10% pour les frappes aériennes (hors missiles et bombes nucléaires)",
      "milestone": true,
      "nameEn": "Thrust vectoring",
      "nameDe": "Schubvektorsteuerung",
      "descEn": "40% chance to evade damage from ground or naval units, 10% for air strikes (excluding missiles and nuclear bombs)",
      "descDe": "40 % Chance, Schaden von Boden- oder Marineeinheiten auszuweichen, 10 % bei Luftangriffen (ausgenommen Raketen und Atombomben)"
    },
    {
      "lvl": 1,
      "type": "active-skill",
      "icon": "⭐",
      "name": "Contre-mesures aériennes",
      "desc": "Dégâts +10% contre les hélicoptères. Après déplacement, mobilité du tour suivant -12 (minimum 2 cases). Mobilité restaurée après un tour de repos à 1 case d'une ville ou d'une unité du génie alliée.",
      "milestone": true,
      "nameEn": "Air countermeasures",
      "nameDe": "Luftabwehrmaßnahmen",
      "descEn": "Damage +10% against helicopters. After moving, next turn's mobility -12 (minimum 2 tiles). Mobility restored after one turn of rest within 1 tile of a city or allied engineer unit.",
      "descDe": "Schaden +10 % gegen Hubschrauber. Nach Bewegung Mobilität der nächsten Runde -12 (mindestens 2 Felder). Mobilität wird nach einer Runde Rast im Umkreis von 1 Feld um eine Stadt oder eine verbündete Pioniereinheit wiederhergestellt."
    },
    {
      "lvl": 1,
      "type": "passive",
      "icon": "🎯",
      "name": "Canon à grande vitesse",
      "desc": "Ignore 25% de la défense ennemie",
      "milestone": true,
      "nameEn": "High-velocity gun",
      "nameDe": "Hochgeschwindigkeitskanone",
      "descEn": "Ignores 25% of enemy defense",
      "descDe": "Ignoriert 25 % der feindlichen Verteidigung"
    },
    {
      "lvl": 1,
      "type": "active-skill",
      "icon": "⭐",
      "name": "Attaque en chaîne",
      "desc": "Dégâts aux blindés et artillerie +20%. Si la cible survit, elle reçoit l'effet Entrave pendant 1 tour. Si elle est anéantie, nouvelle attaque immédiate avec dégâts -30% chaque fois, jusqu'à 1 fois par tour.",
      "milestone": true,
      "nameEn": "Chain attack",
      "nameDe": "Kettenangriff",
      "descEn": "Damage to armor and artillery +20%. If the target survives, it receives the Hinder effect for 1 turn. If it is wiped out, immediate new attack with damage -30% each time, up to 1 time per turn.",
      "descDe": "Schaden gegen Panzer und Artillerie +20 %. Überlebt das Ziel, erhält es den Hemmungseffekt für 1 Runde. Wird es vernichtet, erfolgt sofort ein neuer Angriff mit jedes Mal -30 % Schaden, bis zu 1 Mal pro Runde."
    },
    {
      "lvl": 5,
      "type": "active-skill",
      "icon": "⭐",
      "name": "Vectorisation de poussée Niv.2",
      "desc": "65% de chances d'esquiver les dégâts des unités terrestres ou navales, 20% pour les frappes aériennes (hors missiles et bombes nucléaires)",
      "milestone": false,
      "nameEn": "Thrust vectoring Lv.2",
      "nameDe": "Schubvektorsteuerung Stufe 2",
      "descEn": "65% chance to evade damage from ground or naval units, 20% for air strikes (excluding missiles and nuclear bombs)",
      "descDe": "65 % Chance, Schaden von Boden- oder Marineeinheiten auszuweichen, 20 % bei Luftangriffen (ausgenommen Raketen und Atombomben)"
    },
    {
      "lvl": 5,
      "type": "active-skill",
      "icon": "⭐",
      "name": "Contre-mesures aériennes Niv.2",
      "desc": "Dégâts +20% contre les hélicoptères. Après déplacement, mobilité du tour suivant -9 (minimum 2 cases). Mobilité restaurée après un tour de repos à 1 case d'une ville ou d'une unité du génie alliée.",
      "milestone": false,
      "nameEn": "Air countermeasures Lv.2",
      "nameDe": "Luftabwehrmaßnahmen Stufe 2",
      "descEn": "Damage +20% against helicopters. After moving, next turn's mobility -9 (minimum 2 tiles). Mobility restored after one turn of rest within 1 tile of a city or allied engineer unit.",
      "descDe": "Schaden +20 % gegen Hubschrauber. Nach Bewegung Mobilität der nächsten Runde -9 (mindestens 2 Felder). Mobilität wird nach einer Runde Rast im Umkreis von 1 Feld um eine Stadt oder eine verbündete Pioniereinheit wiederhergestellt."
    },
    {
      "lvl": 5,
      "type": "passive",
      "icon": "🎯",
      "name": "Canon à grande vitesse Niv.2",
      "desc": "Ignore 50% de la défense ennemie",
      "milestone": false,
      "nameEn": "High-velocity gun Lv.2",
      "nameDe": "Hochgeschwindigkeitskanone Stufe 2",
      "descEn": "Ignores 50% of enemy defense",
      "descDe": "Ignoriert 50 % der feindlichen Verteidigung"
    },
    {
      "lvl": 5,
      "type": "active-skill",
      "icon": "⭐",
      "name": "Attaque en chaîne Niv.2",
      "desc": "Dégâts aux blindés et artillerie +30%. Si la cible survit, elle reçoit l'effet Entrave pendant 1 tour. Si elle est anéantie, nouvelle attaque immédiate avec dégâts -30% chaque fois, jusqu'à 2 fois par tour.",
      "milestone": false,
      "nameEn": "Chain attack Lv.2",
      "nameDe": "Kettenangriff Stufe 2",
      "descEn": "Damage to armor and artillery +30%. If the target survives, it receives the Hinder effect for 1 turn. If it is wiped out, immediate new attack with damage -30% each time, up to 2 times per turn.",
      "descDe": "Schaden gegen Panzer und Artillerie +30 %. Überlebt das Ziel, erhält es den Hemmungseffekt für 1 Runde. Wird es vernichtet, erfolgt sofort ein neuer Angriff mit jedes Mal -30 % Schaden, bis zu 2 Mal pro Runde."
    },
    {
      "lvl": 9,
      "type": "active-skill",
      "icon": "⭐",
      "name": "Vectorisation de poussée Niv.3",
      "desc": "90% de chances d'esquiver les dégâts des unités terrestres ou navales, 30% pour les frappes aériennes (hors missiles et bombes nucléaires)",
      "milestone": false,
      "nameEn": "Thrust vectoring Lv.3",
      "nameDe": "Schubvektorsteuerung Stufe 3",
      "descEn": "90% chance to evade damage from ground or naval units, 30% for air strikes (excluding missiles and nuclear bombs)",
      "descDe": "90 % Chance, Schaden von Boden- oder Marineeinheiten auszuweichen, 30 % bei Luftangriffen (ausgenommen Raketen und Atombomben)"
    },
    {
      "lvl": 9,
      "type": "active-skill",
      "icon": "⭐",
      "name": "Contre-mesures aériennes Niv.3",
      "desc": "Dégâts +30% contre les hélicoptères. Après déplacement, mobilité du tour suivant -9 (minimum 2 cases). Mobilité restaurée après un tour de repos à 1 case d'une ville ou d'une unité du génie alliée.",
      "milestone": false,
      "nameEn": "Air countermeasures Lv.3",
      "nameDe": "Luftabwehrmaßnahmen Stufe 3",
      "descEn": "Damage +30% against helicopters. After moving, next turn's mobility -9 (minimum 2 tiles). Mobility restored after one turn of rest within 1 tile of a city or allied engineer unit.",
      "descDe": "Schaden +30 % gegen Hubschrauber. Nach Bewegung Mobilität der nächsten Runde -9 (mindestens 2 Felder). Mobilität wird nach einer Runde Rast im Umkreis von 1 Feld um eine Stadt oder eine verbündete Pioniereinheit wiederhergestellt."
    },
    {
      "lvl": 9,
      "type": "passive",
      "icon": "🎯",
      "name": "Canon à grande vitesse Niv.3",
      "desc": "Ignore 75% de la défense ennemie",
      "milestone": false,
      "nameEn": "High-velocity gun Lv.3",
      "nameDe": "Hochgeschwindigkeitskanone Stufe 3",
      "descEn": "Ignores 75% of enemy defense",
      "descDe": "Ignoriert 75 % der feindlichen Verteidigung"
    },
    {
      "lvl": 9,
      "type": "active-skill",
      "icon": "⭐",
      "name": "Attaque en chaîne Niv.3",
      "desc": "Dégâts aux blindés et artillerie +40%. Si la cible survit, elle reçoit l'effet Entrave pendant 1 tour. Si elle est anéantie, nouvelle attaque immédiate avec dégâts -20% chaque fois, jusqu'à 2 fois par tour.",
      "milestone": false,
      "nameEn": "Chain attack Lv.3",
      "nameDe": "Kettenangriff Stufe 3",
      "descEn": "Damage to armor and artillery +40%. If the target survives, it receives the Hinder effect for 1 turn. If it is wiped out, immediate new attack with damage -20% each time, up to 2 times per turn.",
      "descDe": "Schaden gegen Panzer und Artillerie +40 %. Überlebt das Ziel, erhält es den Hemmungseffekt für 1 Runde. Wird es vernichtet, erfolgt sofort ein neuer Angriff mit jedes Mal -20 % Schaden, bis zu 2 Mal pro Runde."
    },
    {
      "lvl": 11,
      "type": "active-skill",
      "icon": "⭐",
      "name": "Contre-mesures aériennes Niv.4",
      "desc": "Dégâts +40% contre les hélicoptères. Après déplacement, mobilité du tour suivant -6 (minimum 2 cases). Mobilité restaurée après un tour de repos à 1 case d'une ville ou d'une unité du génie alliée.",
      "milestone": false,
      "nameEn": "Air countermeasures Lv.4",
      "nameDe": "Luftabwehrmaßnahmen Stufe 4",
      "descEn": "Damage +40% against helicopters. After moving, next turn's mobility -6 (minimum 2 tiles). Mobility restored after one turn of rest within 1 tile of a city or allied engineer unit.",
      "descDe": "Schaden +40 % gegen Hubschrauber. Nach Bewegung Mobilität der nächsten Runde -6 (mindestens 2 Felder). Mobilität wird nach einer Runde Rast im Umkreis von 1 Feld um eine Stadt oder eine verbündete Pioniereinheit wiederhergestellt."
    },
    {
      "lvl": 12,
      "type": "active-skill",
      "icon": "⭐",
      "name": "Attaque en chaîne Niv.4",
      "desc": "Dégâts aux blindés et artillerie +50%. Si la cible survit, elle reçoit l'effet Entrave pendant 1 tour. Si elle est anéantie, nouvelle attaque immédiate avec dégâts -20% chaque fois, jusqu'à 3 fois par tour.",
      "milestone": false,
      "nameEn": "Chain attack Lv.4",
      "nameDe": "Kettenangriff Stufe 4",
      "descEn": "Damage to armor and artillery +50%. If the target survives, it receives the Hinder effect for 1 turn. If it is wiped out, immediate new attack with damage -20% each time, up to 3 times per turn.",
      "descDe": "Schaden gegen Panzer und Artillerie +50 %. Überlebt das Ziel, erhält es den Hemmungseffekt für 1 Runde. Wird es vernichtet, erfolgt sofort ein neuer Angriff mit jedes Mal -20 % Schaden, bis zu 3 Mal pro Runde."
    }
  ],
  "recommendedGenerals": [],
  "levelingPriority": [
    "Débloquer les perks milestones (5, 9, 12) en priorité",
    "Les perks stat sont moins prioritaires que les active-skills",
    "À partir du niveau 9, spécialiser selon votre style : offensif ou défensif"
  ],
  "faqs": [
    {
      "q": "Comment débloquer Harrier dans World Conqueror 4 ?",
      "a": "Harrier se débloque via la boutique d'élite pour 30 items d'élite (aérienne). Tier A — un palier fort, positionnée juste sous l'élite absolue mais largement compétitive en conquête et en PvP."
    },
    {
      "q": "Quelles sont les statistiques maximales de Harrier au niveau 12 ?",
      "a": "Au niveau 12, Harrier culmine à 118 en attaque pour une portée de 3. Les unités aériennes ne possèdent pas de défense ni de HP exploitables en combat — leur valeur se lit sur la frappe et le rayon d'action. Profil aérien solide — frappe et survie au-dessus des avions standards, efficace en appui ou en interception."
    },
    {
      "q": "Quels perks milestone débloque Harrier ?",
      "a": "Harrier ne possède pas de perks milestone aux paliers 5, 9 ou 12 — l'unité s'appuie principalement sur ses bonus de niveau 1 et sur la montée en statistiques brutes. Priorisez les niveaux qui augmentent HP et attaque."
    },
    {
      "q": "Combien coûte l'amélioration complète de Harrier jusqu'au niveau 12 ?",
      "a": "Cumul niveaux 1 → 12 pour Harrier : ~244.2k d'énergie, ~344.6k d'or, 780 items d'élite, 60 badges. Le principal goulot est l'or et les items d'élite — visez les niveaux milestone 5, 9 et 12 en premier plutôt que de lisser les upgrades intermédiaires."
    },
    {
      "q": "Quels généraux s'associent le mieux avec Harrier ?",
      "a": "Associez-la à des généraux à spécialité Air (Göring, Tedder, Arnold, Kawabe) avec compétences Supériorité aérienne ou Appui tactique. Les bonus d'attaque aérienne et de rayon d'action transforment l'unité en arme d'ouverture."
    },
    {
      "q": "Dans quels scénarios Harrier est-elle la plus utile ?",
      "a": "Utilisez-la en appui tactique sur les cartes à objectifs rapprochés. Elle gère l'interception et le nettoyage au sol sans exiger un slot S-tier."
    }
  ],
  "sources": [
    "https://world-conqueror-4.fandom.com/wiki/Elite_Force",
    "https://en.namu.wiki/w/%EC%84%B8%EA%B3%84%20%EC%A0%95%EB%B3%B5%EC%9E%90%204/%EC%97%98%EB%A6%AC%ED%8A%B8%20%EB%B6%80%EB%8C%80"
  ],
  "armyId": 350001,
  "tierCosts": [
    {
      "level": 1,
      "needHQLv": 0,
      "costGold": 0,
      "costIndustry": 0,
      "costEnergy": 0,
      "costTech": 0,
      "costItem": 30,
      "costBadge": 0
    },
    {
      "level": 2,
      "needHQLv": 0,
      "costGold": 3750,
      "costIndustry": 0,
      "costEnergy": 1500,
      "costTech": 0,
      "costItem": 5,
      "costBadge": 0
    },
    {
      "level": 3,
      "needHQLv": 0,
      "costGold": 13200,
      "costIndustry": 0,
      "costEnergy": 7125,
      "costTech": 0,
      "costItem": 15,
      "costBadge": 0
    },
    {
      "level": 4,
      "needHQLv": 0,
      "costGold": 20700,
      "costIndustry": 0,
      "costEnergy": 12375,
      "costTech": 0,
      "costItem": 30,
      "costBadge": 0
    },
    {
      "level": 5,
      "needHQLv": 0,
      "costGold": 41250,
      "costIndustry": 0,
      "costEnergy": 30000,
      "costTech": 0,
      "costItem": 60,
      "costBadge": 0
    },
    {
      "level": 6,
      "needHQLv": 0,
      "costGold": 49500,
      "costIndustry": 0,
      "costEnergy": 36000,
      "costTech": 0,
      "costItem": 70,
      "costBadge": 0
    },
    {
      "level": 7,
      "needHQLv": 0,
      "costGold": 59400,
      "costIndustry": 0,
      "costEnergy": 43200,
      "costTech": 0,
      "costItem": 80,
      "costBadge": 0
    },
    {
      "level": 8,
      "needHQLv": 0,
      "costGold": 71280,
      "costIndustry": 0,
      "costEnergy": 51840,
      "costTech": 0,
      "costItem": 90,
      "costBadge": 0
    },
    {
      "level": 9,
      "needHQLv": 0,
      "costGold": 85550,
      "costIndustry": 0,
      "costEnergy": 62200,
      "costTech": 0,
      "costItem": 100,
      "costBadge": 0
    },
    {
      "level": 10,
      "needHQLv": 0,
      "costGold": 0,
      "costIndustry": 0,
      "costEnergy": 0,
      "costTech": 0,
      "costItem": 100,
      "costBadge": 10
    },
    {
      "level": 11,
      "needHQLv": 0,
      "costGold": 0,
      "costIndustry": 0,
      "costEnergy": 0,
      "costTech": 0,
      "costItem": 100,
      "costBadge": 20
    },
    {
      "level": 12,
      "needHQLv": 0,
      "costGold": 0,
      "costIndustry": 0,
      "costEnergy": 0,
      "costTech": 0,
      "costItem": 100,
      "costBadge": 30
    }
  ],
  "image": {
    "sprite": "/img/wc4/elites/350001.png",
    "lvl12": null
  },
  "shortDescEn": "British VTOL combat aircraft (vertical take-off and landing).",
  "shortDescDe": "Britisches VTOL-Kampfflugzeug (Senkrechtstarter).",
  "longDescEn": "The first operational VTOL combat aircraft. Famous for its role in the Falklands War.",
  "longDescDe": "Das erste einsatzfähige VTOL-Kampfflugzeug. Berühmt für seine Rolle im Falklandkrieg.",
  "faqsEn": [
    {
      "q": "How do you unlock Harrier in World Conqueror 4?",
      "a": "Harrier is unlocked from the Elite Shop for 30 elite items (air category). It sits at tier A — a strong tier, sitting just below the absolute elite but fully competitive in Conquest and PvP."
    },
    {
      "q": "What are Harrier's maximum stats at level 12?",
      "a": "At level 12, Harrier peaks at 118 attack with range 3. Aircraft do not expose meaningful defense or HP values in combat — their worth is read in raw strike power and range. Solid air profile — damage and survivability above standard planes, effective in support or intercept."
    },
    {
      "q": "Which milestone perks does Harrier unlock?",
      "a": "Harrier does not carry milestone perks at levels 5, 9 or 12 — the unit leans mainly on its level-1 passives and on raw stat growth. Prioritize upgrades that lift HP and attack."
    },
    {
      "q": "How expensive is fully upgrading Harrier to level 12?",
      "a": "Cumulative cost levels 1 → 12 for Harrier: ~244.2k energy, ~344.6k gold, 780 elite items, 60 badges. The main bottleneck is gold and elite items — hit the milestone levels 5, 9 and 12 first rather than evenly smoothing intermediate upgrades."
    },
    {
      "q": "Which generals pair best with Harrier?",
      "a": "Pair it with Air-specialty generals (Göring, Tedder, Arnold, Kawabe) running Air Supremacy or Tactical Support. Air-attack and range bonuses turn the unit into an opening weapon."
    },
    {
      "q": "In which scenarios is Harrier most useful?",
      "a": "Use it as tactical support on tight-objective maps. It handles intercept and ground clean-up without demanding an S-tier slot."
    }
  ],
  "faqsDe": [
    {
      "q": "Wie schaltet man Harrier in World Conqueror 4 frei?",
      "a": "Harrier wird im Elite-Shop für 30 Elite-Items freigeschaltet (Kategorie Luftwaffe). Stufe A — eine starke Stufe, knapp unter der absoluten Elite aber voll konkurrenzfähig in Conquest und PvP."
    },
    {
      "q": "Wie lauten die maximalen Werte von Harrier auf Stufe 12?",
      "a": "Auf Stufe 12 erreicht Harrier 118 Angriff bei Reichweite 3. Flugzeuge haben im Kampf keine aussagekräftigen Verteidigungs- oder HP-Werte — ihr Wert bemisst sich an roher Schlagkraft und Reichweite. Solides Luftprofil — Schaden und Überlebensfähigkeit über Standardflugzeugen, effektiv in Unterstützung oder Abfangjagd."
    },
    {
      "q": "Welche Meilenstein-Perks schaltet Harrier frei?",
      "a": "Harrier besitzt keine Meilenstein-Perks auf Stufe 5, 9 oder 12 — die Einheit stützt sich hauptsächlich auf die Stufe-1-Passiva und das Rohwert-Wachstum. Stufen priorisieren, die HP und Angriff anheben."
    },
    {
      "q": "Wie teuer ist die volle Aufrüstung von Harrier auf Stufe 12?",
      "a": "Kumulative Kosten Stufe 1 → 12 für Harrier: ~244.2k Energie, ~344.6k Gold, 780 Elite-Items, 60 Abzeichen. Der Hauptengpass sind Gold und Elite-Items — zuerst die Meilensteine 5, 9 und 12 ansteuern, statt Zwischenstufen gleichmäßig hochzuziehen."
    },
    {
      "q": "Welche Generäle passen am besten zu Harrier?",
      "a": "Kombinieren Sie sie mit Luft-Spezialisten (Göring, Tedder, Arnold, Kawabe) und Luftüberlegenheit oder Taktischer Unterstützung. Luftangriffs- und Reichweitenboni machen die Einheit zur Eröffnungswaffe."
    },
    {
      "q": "In welchen Szenarien ist Harrier am nützlichsten?",
      "a": "Als taktische Unterstützung auf Karten mit engen Zielen einsetzen. Sie übernimmt Abfangjagd und Bodenreinigung, ohne einen S-Tier-Slot zu verlangen."
    }
  ]
}
