{
  "slug": "cotton",
  "name": "Cotton",
  "nameEn": "Cotton",
  "nameCanonical": "Cotton",
  "faction": "standard",
  "category": "cavalry",
  "rank": "S",
  "quality": "gold",
  "country": "GB",
  "countryName": "Grande-Bretagne",
  "shortDesc": "Général cavalry — Grande-Bretagne.",
  "longDesc": "Cotton — commandant de l'ère 1800-1914 dans European War 6. Fiche générée automatiquement depuis les fichiers de jeu ; à enrichir.",
  "skills": [
    {
      "name": "Maneuver",
      "nameEn": "Maneuver",
      "desc": "0% chance to ignore the effect of barriers when using cavalry to attack",
      "rating": null,
      "stars": null,
      "icon": "/img/ew6/skills/skill_21.webp",
      "replaceable": false,
      "replaceableReason": null,
      "skillType": 21,
      "skillLevel": 1,
      "skillSlug": "maneuver",
      "slot": 1
    },
    {
      "name": "Edge",
      "nameEn": "Edge",
      "desc": "0 additional damage when cavalry attack infantry",
      "rating": null,
      "stars": null,
      "icon": "/img/ew6/skills/skill_23.webp",
      "replaceable": false,
      "replaceableReason": null,
      "skillType": 23,
      "skillLevel": 2,
      "skillSlug": "edge",
      "slot": 2
    },
    {
      "name": "Tactic Master",
      "nameEn": "Tactic Master",
      "desc": "0% chance of a second attack after attacking",
      "rating": null,
      "stars": null,
      "icon": "/img/ew6/skills/skill_7.webp",
      "replaceable": false,
      "replaceableReason": null,
      "skillType": 7,
      "skillLevel": 2,
      "skillSlug": "tactic-master",
      "slot": 3
    }
  ],
  "attributes": {
    "infantry": null,
    "cavalry": {
      "start": 0,
      "max": 1
    },
    "artillery": null,
    "navy": null
  },
  "hasTrainingPath": false,
  "training": null,
  "acquisition": {
    "type": "medals",
    "cost": 1000,
    "currency": "medals",
    "notes": "Donnée extraite de GeneralSettings — à vérifier"
  },
  "bonuses": [],
  "recommendedUnits": [],
  "sources": [
    "Données extraites des fichiers de jeu European War 6: 1914"
  ],
  "skillSlots": 3,
  "unlockHQLv": 14,
  "militaryRank": 14,
  "gameId": 1037,
  "image": {
    "photo": "/img/ew6/generals/Cotton.webp",
    "head": "/img/ew6/heads/Cotton.webp",
    "photoTrained": null,
    "headTrained": null
  },
  "trainedSkills": null
}