{
  "slug": "hartmann",
  "name": "Erich Hartmann",
  "nameEn": "Hartmann",
  "faction": "standard",
  "category": "airforce",
  "rank": "S",
  "quality": "gold",
  "country": "DE",
  "countryName": "Allemagne",
  "shortDesc": "Général aérienne or — Allemagne.",
  "longDesc": "Erich Hartmann est un général aérienne de qualité or — Allemagne. Données extraites du jeu — descriptions et conseils tactiques à confirmer.",
  "skills": [
    {
      "slot": 1,
      "name": "Eagle Fly",
      "desc": "Boosts 40% dodge rate and 4 mobility when commanding an air hover unit, and decreases 30% taken damage from air forces. Boost critical strike damage 1% based on 1% dodge rate when air hovering units attack.",
      "rating": null,
      "stars": null,
      "icon": "/img/wc4/skills/general_skill_152.png",
      "replaceable": false,
      "replaceableReason": null,
      "nameEn": "Eagle Fly",
      "skillSlug": "eagle-fly",
      "skillType": 152,
      "skillLevel": 5
    },
    {
      "slot": 2,
      "name": "Airforce Leader",
      "desc": "40% chance to give the enemy a critical attack when commanding air units",
      "rating": null,
      "stars": null,
      "icon": "/img/wc4/skills/general_skill_22.webp",
      "replaceable": false,
      "replaceableReason": null,
      "nameEn": "Airforce Leader",
      "skillSlug": "airforce-leader",
      "skillType": 22,
      "skillLevel": 5
    },
    {
      "slot": 3,
      "name": "Carpet Bombing",
      "desc": "Damage +32% to the defending forces in the city when air-raiding",
      "rating": null,
      "stars": null,
      "icon": "/img/wc4/skills/general_skill_41.webp",
      "replaceable": false,
      "replaceableReason": null,
      "nameEn": "Carpet Bombing",
      "skillSlug": "carpet-bombing",
      "skillType": 41,
      "skillLevel": 4
    },
    {
      "slot": 4,
      "name": "Fluke",
      "desc": "When commanded troop activates dodge, restore 15% based on self's maximum HP (up to 1 time per turn)",
      "rating": null,
      "stars": null,
      "icon": "/img/wc4/skills/general_skill_142.webp",
      "replaceable": false,
      "replaceableReason": null,
      "nameEn": "Fluke",
      "skillSlug": "fluke",
      "skillType": 142,
      "skillLevel": 5
    },
    {
      "slot": 5,
      "name": "Inferior Victory",
      "desc": "Damage is increased by 16% when the number of troop formations under command is 1.",
      "rating": null,
      "stars": null,
      "icon": "/img/wc4/skills/general_skill_131.webp",
      "replaceable": false,
      "replaceableReason": null,
      "nameEn": "Inferior Victory",
      "skillSlug": "inferior-victory",
      "skillType": 131,
      "skillLevel": 4
    }
  ],
  "attributes": {
    "infantry": {
      "start": 0,
      "max": 0
    },
    "artillery": {
      "start": 3,
      "max": 3
    },
    "armor": {
      "start": 0,
      "max": 0
    },
    "navy": {
      "start": 0,
      "max": 0
    },
    "airforce": {
      "start": 6,
      "max": 6
    },
    "marching": {
      "start": 3,
      "max": 5
    }
  },
  "hasTrainingPath": true,
  "training": null,
  "acquisition": {
    "type": "medals",
    "cost": 6985,
    "currency": "medals",
    "notes": "Données de jeu — à vérifier"
  },
  "bonuses": [],
  "recommendedUnits": [],
  "sources": [
    "https://world-conqueror-4.fandom.com/wiki/Generals",
    "Données extraites des fichiers de jeu World Conqueror 4"
  ],
  "nameCanonical": "Hartmann",
  "skillSlots": 5,
  "unlockHQLv": 1,
  "militaryRank": 7,
  "gameId": 1108,
  "image": {
    "photo": "/img/wc4/generals/Hartmann.webp",
    "head": "/img/wc4/heads/Hartmann.webp",
    "photoTrained": null,
    "headTrained": null
  },
  "shortDescEn": "Gold air force general — Germany.",
  "shortDescDe": "Gold Luftwaffen-General — Deutschland.",
  "longDescEn": "Erich Hartmann is a gold-quality air force general — Germany. Data extracted from the game — descriptions and tactical notes to be confirmed.",
  "longDescDe": "Erich Hartmann ist ein Gold-Luftwaffen-General — Deutschland. Daten aus dem Spiel extrahiert — Beschreibungen und taktische Hinweise noch zu bestätigen."
}
